marge/__init__.py
marge/main.py
marge/autotuning/__init__.py
marge/autotuning/autotuning.py
marge/configs/__init__.py
marge/configs/hw_config.py
marge/configs/sys_config.py
marge/configs/units.py
marge/controller/__init__.py
marge/controller/controller_console.py
marge/controller/controller_figures.py
marge/controller/controller_history_list.py
marge/controller/controller_imageview.py
marge/controller/controller_main.py
marge/controller/controller_menu.py
marge/controller/controller_plot1d.py
marge/controller/controller_plot3d.py
marge/controller/controller_post.py
marge/controller/controller_postprocessing.py
marge/controller/controller_preprocessing.py
marge/controller/controller_processing.py
marge/controller/controller_protocol_inputs.py
marge/controller/controller_protocol_list.py
marge/controller/controller_reconstruction.py
marge/controller/controller_sequence_inputs.py
marge/controller/controller_sequence_list.py
marge/controller/controller_session.py
marge/controller/controller_smith_chart.py
marge/controller/controller_toolbar_figures.py
marge/controller/controller_toolbar_marcos.py
marge/controller/controller_toolbar_post.py
marge/controller/controller_toolbar_protocols.py
marge/controller/controller_toolbar_sequences.py
marge/controller/controller_visualisation.py
marge/controller/experiment_gui.py
marge/docs/__init__.py
marge/docs/source/__init__.py
marge/docs/source/conf.py
marge/manager/__init__.py
marge/manager/dicommanager.py
marge/marcos/__init__.py
marge/marcos/marcos_client/__init__.py
marge/marcos/marcos_client/examples.py
marge/marcos/marcos_client/experiment.py
marge/marcos/marcos_client/grad_board.py
marge/marcos/marcos_client/local_config.py
marge/marcos/marcos_client/marcompile.py
marge/marcos/marcos_client/marcostek.py
marge/marcos/marcos_client/marmachine.py
marge/marcos/marcos_client/plot_csv.py
marge/marcos/marcos_client/server_comms.py
marge/marcos/marcos_client/test_base.py
marge/marcos/marcos_client/test_gpa_fhdo.py
marge_mri_example-0.0.8.dist-info/licenses/LICENSE
marge_mri_example-0.0.8.dist-info/METADATA
marge_mri_example-0.0.8.dist-info/WHEEL
marge_mri_example-0.0.8.dist-info/top_level.txt
marge_mri_example-0.0.8.dist-info/RECORD
