Metadata-Version: 2.4
Name: marge-mri-example
Version: 0.0.8
Summary: Une description courte de votre projet
Author: Nihal Ouahabi
Author-email: Nihal <votre.email@example.com>
Classifier: Programming Language :: Python :: 3
Classifier: License :: OSI Approved :: MIT License
Classifier: Operating System :: OS Independent
Requires-Python: >=3.10
License-File: LICENSE
Requires-Dist: requests>=2.25.1
Requires-Dist: numpy>=1.20.0
Requires-Dist: matplotlib
Requires-Dist: nibabel
Requires-Dist: pydicom
Requires-Dist: scipy
Requires-Dist: msgpack
Requires-Dist: PyQt5
Requires-Dist: pyqtgraph
Requires-Dist: QDarkStyle
Requires-Dist: bm4d
Requires-Dist: phantominator
Requires-Dist: pyserial
Requires-Dist: ismrmrd
Requires-Dist: pypulseq
Requires-Dist: marga_pulseq
Requires-Dist: scikit-learn
Requires-Dist: scikit-image
Requires-Dist: imageio
Requires-Dist: h5py
Dynamic: author
Dynamic: license-file
